[{"source": "https://www.youtube.com/feeds/videos.xml?channel_id=UCme4ZOv65uzGADXuvtHkSvA", "title": "1 Ksi\u0119ga Samuela || Rozdzia\u0142 01", "description": "Przeczytajmy razem ca\u0142e Pismo \u015awi\u0119te! Od 1 pa\u017adziernika 2020 czytamy Pismo \u015awi\u0119te, codziennie 1 rozdzia\u0142 \u017cyciodajnego S\u0141OWA BOGA.\nWykorzystano Najnowszy przek\u0142ad Pisma \u015awi\u0119tego z komentarzem opracowany przez Zesp\u00f3\u0142 Biblist\u00f3w Polskich z inicjatywy Towarzystwa \u015awi\u0119tego Paw\u0142a (Edycja \u015awi\u0119tego Paw\u0142a). Pierwszy przek\u0142ad w trzecim tysi\u0105cleciu.\n________________________________________\nAby nas wesprze\u0107 kliknij tu \n\u2192 https://patronite.pl/langustanapalmie\n\u2192 http://bit.ly/Subskrybuj_Languste\n\n\u2661 Historie pot\u0142uczone\nAnchor \u2192 https://anchor.fm/langusta-na-palmie\nSpreaker \u2192 https://www.spreaker.com/show/historie-potluczone\nSpotify \u2192 https://spoti.fi/2NVIRHb\nApple \u2192 https://apple.co/2ZIPQZv\nGoogle Podcasts \u2192 https://bit.ly/2OlBWH\n\n\u2661  Pismo \u015awi\u0119te: \nAnchor \u2192 https://anchor.fm/langusta-na-palmie\nSpreaker \u2192 https://www.spreaker.com/show/przeczytaj-pismo-swiete-z-langusta\nSpotify \u2192  https://spoti.fi/34nZwLr\nApple \u2192  https://apple.co/33zdwCV\nGoogle Podcasts \u2192 https://bit.ly/3nmaZUc\n\nStrona z kalendarzem o. Adama: \n\u2192 http://www.langustanapalmie.pl\nMo\u017cna nas r\u00f3wnie\u017c znale\u017a\u0107 na Facebooku: \n\u2192 https://www.facebook.com/LangustaNaPalmie\nTwitterze: \n\u2192 https://twitter.com/LangustaPalmowa\nInstagramie: \n\u2192 https://www.instagram.com/langustanapalmie/\n\nZapraszamy.", "link": "https://www.youtube.com/watch?v=zDS6iKyHnBQ", "date_published": "2021-12-20 00:00:00+00:00", "persistent": false, "user": null, "language": "pl-PL"}, {"source": "https://www.youtube.com/feeds/videos.xml?channel_id=UCme4ZOv65uzGADXuvtHkSvA", "title": "Ju\u017c si\u0119 nie wstydz\u0119 | Premiera 25 grudnia!", "description": "Trasa \"Ju\u017c si\u0119 nie wstydz\u0119\" to wyj\u0105tkowe spotkania, kt\u00f3re odby\u0142y si\u0119 tej jesieni, w ponad dwudziestu miastach w Polsce. Tre\u015b\u0107, emocje i wzruszenie, kt\u00f3re nam towarzyszy\u0142y podczas ich trwania, postanowili\u015bmy zarejestrowa\u0107 tak \u017ceby m\u00f3c prze\u017cy\u0107 je jeszcze niejeden raz... wsp\u00f3lnie z Wami! Kliknij przycisk: ustaw przypomnienie i widzimy si\u0119 tutaj pierwszego dnia \u015awi\u0105t Bo\u017cego Narodzenia \u2b50\ufe0f.  Nie mo\u017cemy si\u0119 doczeka\u0107, a TY? \ud83e\udd0d \n\n\u2b50\ufe0f\u2b50\ufe0f\u2b50\ufe0f\nLINK do premiery:\n\n\u2192 https://youtu.be/cE5sqiHeaK8\n\n________________________________________\nAby nas wesprze\u0107 kliknij tu \n\u2192 https://patronite.pl/langustanapalmie\n\u2192 http://bit.ly/Subskrybuj_Languste\n\n\u2661 Historie pot\u0142uczone\nAnchor \u2192 https://anchor.fm/langusta-na-palmie\nSpreaker \u2192 https://www.spreaker.com/show/historie-potluczone\nSpotify \u2192 https://spoti.fi/2NVIRHb\nApple \u2192 https://apple.co/2ZIPQZv\nGoogle Podcasts \u2192 https://bit.ly/2OlBWH\n\n\u2661  Pismo \u015awi\u0119te: \nAnchor \u2192 https://anchor.fm/langusta-na-palmie\nSpreaker \u2192 https://www.spreaker.com/show/przeczytaj-pismo-swiete-z-langusta\nSpotify \u2192  https://spoti.fi/34nZwLr\nApple \u2192  https://apple.co/33zdwCV\nGoogle Podcasts \u2192 https://bit.ly/3nmaZUc\n\nStrona z kalendarzem o. Adama: \n\u2192 http://www.langustanapalmie.pl\nMo\u017cna nas r\u00f3wnie\u017c znale\u017a\u0107 na Facebooku: \n\u2192 https://www.facebook.com/LangustaNaPalmie\nTwitterze: \n\u2192 https://twitter.com/LangustaPalmowa\nInstagramie: \n\u2192 https://www.instagram.com/langustanapalmie/\n\nZapraszamy.", "link": "https://www.youtube.com/watch?v=ofc8wLEEp80", "date_published": "2021-12-20 00:00:00+00:00", "persistent": false, "user": null, "language": "pl-PL"}, {"source": "https://www.youtube.com/feeds/videos.xml?channel_id=UCme4ZOv65uzGADXuvtHkSvA", "title": "Kol\u0119dy dla rado\u015bci [01] Jest taki dzie\u0144", "description": "Fundacja Malak wraz z Rafa\u0142em Maciejewskim postanowi\u0142a wyprodukowa\u0107 cztery \u015bwi\u0105teczne songi. S\u0105 w\u015br\u00f3d nich dwie tradycyjne kol\u0119dy, pastora\u0142ka i \u015bwi\u0105teczny hicior. Wszystko w nowoczesnej aran\u017cacji, kt\u00f3r\u0105 stworzy\u0142 Mateusz Banasiuk. Zdecydowali\u015bmy si\u0119 zagra\u0107 kol\u0119dy, bo chcemy wsp\u00f3lnie da\u0107 ludziom troch\u0119 rado\u015bci i u\u015bmiechu. Bo\u017ce Narodzenie to czas kiedy zn\u00f3w przypominamy sobie, \u017ce B\u00f3g w Jezusie sta\u0142 si\u0119 naszym bratem, bliskim, wsp\u00f3\u0142czuj\u0105cym, rozumiej\u0105cym - opowiada - a to wszystko zdecydowanie powody do u\u015bmiechu. \nRafa\u0142 zebra\u0142 swoich uczni\u00f3w, przyjaci\u00f3\u0142, ludzi, z kt\u00f3rymi \u015bpiewa przy r\u00f3\u017cnych okazjach, z kt\u00f3rymi zna si\u0119 od dominikan\u00f3w i w ten spos\u00f3b powsta\u0142 nasz \u015bwi\u0105teczny boysband. \n\nOsiem m\u0119skich g\u0142os\u00f3w zapowiadaj\u0105cych nam Dobr\u0105 Nowin\u0119. \n\nMUZYKA:\n\naran\u017cacja: Mateusz Banasiuk\nrealizacja nagrania: Damian Posi\u0142a\nedycja/mix/mastering: Mateusz Banasiuk\n\ntenory: \nTymoteusz Ekert\nMateusz Banasiuk\n\nbarytony: \nRafa\u0142 Maciejewski\nJakub Pokorski\nDamian Posi\u0142a\n\nbasy:\nPawe\u0142 Banach\nSzymon D\u0119bkowski\nKamil Gruszczy\u0144ski\nMicha\u0142 Buczek\n\n\u2014\n\nVIDEO:\n\nzdj\u0119cia: Micha\u0142 Buczek, Emil Ksi\u0105\u017cczak\nmonta\u017c: Micha\u0142 Buczek\no\u015bwietlenie: Bart\u0142omiej Borcz\nprodukcja i scenografia: Fundacja Malak\n\nwww.fundacjamalak.pl\n\n@Langustanapalmie @FundacjamalakPl \n________________________________________\nAby nas wesprze\u0107 kliknij tu \n\u2192 https://patronite.pl/langustanapalmie\n\u2192 http://bit.ly/Subskrybuj_Languste\n\n\u2661 Historie pot\u0142uczone\nAnchor \u2192 https://anchor.fm/langusta-na-palmie\nSpreaker \u2192 https://www.spreaker.com/show/historie-potluczone\nSpotify \u2192 https://spoti.fi/2NVIRHb\nApple \u2192 https://apple.co/2ZIPQZv\nGoogle Podcasts \u2192 https://bit.ly/2OlBWH\n\n\u2661  Pismo \u015awi\u0119te: \nAnchor \u2192 https://anchor.fm/langusta-na-palmie\nSpreaker \u2192 https://www.spreaker.com/show/przeczytaj-pismo-swiete-z-langusta\nSpotify \u2192  https://spoti.fi/34nZwLr\nApple \u2192  https://apple.co/33zdwCV\nGoogle Podcasts \u2192 https://bit.ly/3nmaZUc\n\nStrona z kalendarzem o. Adama: \n\u2192 http://www.langustanapalmie.pl\nMo\u017cna nas r\u00f3wnie\u017c znale\u017a\u0107 na Facebooku: \n\u2192 https://www.facebook.com/LangustaNaPalmie\nTwitterze: \n\u2192 https://twitter.com/LangustaPalmowa\nInstagramie: \n\u2192 https://www.instagram.com/langustanapalmie/\n\nZapraszamy.", "link": "https://www.youtube.com/watch?v=1mL-1I-WOFc", "date_published": "2021-12-20 00:00:00+00:00", "persistent": false, "user": null, "language": "pl-PL"}, {"source": "https://www.youtube.com/feeds/videos.xml?channel_id=UCme4ZOv65uzGADXuvtHkSvA", "title": "Wyszynki [#972] Obrona", "description": "Wstawaj, \u017cyj i kochaj, czyli poranna dawka energii na ca\u0142y dzie\u0144 i nie tylko. \n\n\"Wstawaki 2.0\" muz: Jan Smoczy\u0144ski || Agnieszka Musia\u0142\n#Wstawaki #zr\u00f3bmydobrydzie\u0144 #AdamSzustakOP\n________________________________________\nZapraszamy Was do w\u0142\u0105czenia si\u0119 w Adwentow\u0105 Akcj\u0119 Charytatywn\u0105:\n\u2192 https://charytatywnie.fundacjamalak.pl/  \n________________________________________\nKsi\u0105\u017ck\u0119 znajdziecie tu \u2661\n\u2192 https://langustanapalmie.pl/produkt/jaksiemodlic/\n\nKsi\u0105\u017cka cegie\u0142ka (w wersji papierowej) wyruszy do Was w drog\u0119 ju\u017c 12 listopada.\nEbook - dost\u0119pny ju\u017c dzi\u015b.\n\nKsi\u0105\u017cka jest cegie\u0142k\u0105 i ca\u0142y doch\u00f3d ze sprzeda\u017cy jest przeznaczony na dzia\u0142alno\u015b\u0107 Niez\u0142ej Fundacji zajmuj\u0105cej si\u0119 dzie\u0142ami Langusty Na Palmie.\n________________________________________\nAby nas wesprze\u0107 kliknij tu \n\u2192 https://patronite.pl/langustanapalmie\n\u2192 http://bit.ly/Subskrybuj_Languste\n\n\u2661 Historie pot\u0142uczone\nAnchor \u2192 https://anchor.fm/langusta-na-palmie\nSpreaker \u2192 https://www.spreaker.com/show/historie-potluczone\nSpotify \u2192 https://spoti.fi/2NVIRHb\nApple \u2192 https://apple.co/2ZIPQZv\nGoogle Podcasts \u2192 https://bit.ly/2OlBWH\n\n\u2661  Pismo \u015awi\u0119te: \nAnchor \u2192 https://anchor.fm/langusta-na-palmie\nSpreaker \u2192 https://www.spreaker.com/show/przeczytaj-pismo-swiete-z-langusta\nSpotify \u2192  https://spoti.fi/34nZwLr\nApple \u2192  https://apple.co/33zdwCV\nGoogle Podcasts \u2192 https://bit.ly/3nmaZUc\n\nStrona z kalendarzem o. Adama: \n\u2192 http://www.langustanapalmie.pl\nMo\u017cna nas r\u00f3wnie\u017c znale\u017a\u0107 na Facebooku: \n\u2192 https://www.facebook.com/LangustaNaPalmie\nTwitterze: \n\u2192 https://twitter.com/LangustaPalmowa\nInstagramie: \n\u2192 https://www.instagram.com/langustanapalmie/\n\nZapraszamy.", "link": "https://www.youtube.com/watch?v=iXGGzWJxKjc", "date_published": "2021-12-20 00:00:00+00:00", "persistent": false, "user": null, "language": "pl-PL"}, {"source": "https://www.youtube.com/feeds/videos.xml?channel_id=UCme4ZOv65uzGADXuvtHkSvA", "title": "Aloes", "description": "Cztery niedziele Adwentu i cztery piosenki na A. \nZapraszamy w krain\u0119 S\u0141OWA, MUZYKI i OBRAZU. \n\n@Langustanapalmie  @AgnieszkaMusiaYT \n\ntekst: Agnieszka Musia\u0142 II Jan Smoczy\u0144ski \nmuzyka: Agnieszka Musia\u0142 II Jan Smoczy\u0144ski \nzesp\u00f3\u0142 w sk\u0142adzie: Agnieszka Musia\u0142 || Jan Smoczy\u0144ski || Kamil Siciak\nprodukcja serii, scenografia, stylizacja: Sylwia Smoczy\u0144ska \nrealizacja i produkcja muzyki: Jan Smoczy\u0144ski \nzdj\u0119cia: Marcin Jo\u0144czyk \nmonta\u017c: Marcin Kopiec \nrealizacja \u015bwiat\u0142a: Bartek Borcz \npomoc techniczna: Micha\u0142 Blicharski \nmake up: Zuza G\u00f3rska \nZdj\u0119cia zrealizowano w Agroturystyce Modry Ganek\n\n\"Aloes\"\n\nzwr. 1\nM\u00f3wi\u0105 do mnie, ze nie warto \nI\u015b\u0107 za g\u0142osem serca\nRezygnuj\u0119 z moich pragnie\u0144 \nInni wiedz\u0105 lepiej\nwci\u0105\u017c nie widz\u0119 \nKo\u0144ca zmaga\u0144 \ndroga mnie wyka\u0144cza \nNie chce d\u0142u\u017cej si\u0119 poddawa\u0107 \nNie chce walczy\u0107 sama \n\nref.\nTwoje s\u0142owa jak aloes\n\u0141agodz\u0105 ka\u017cdy b\u00f3l\nJeszcze nie wszystko stracone \nUuu\njak aloes \u0142agodzisz \nKa\u017cdy m\u00f3j trud \nJeszcze nie wszystko stracone \nAloes \n\nZwr. 2 \nNie poddaj\u0119 si\u0119 naciskom \nSerce s\u0142yszy prawd\u0119 \nGdzie nadzieja tam marzenia \nNigdy nie jest za p\u00f3\u017ano \n\nRef.\nTwoje s\u0142owa jak aloes\n\u0141agodz\u0105 ka\u017cdy b\u00f3l\nJeszcze nie wszystko stracone \nUuu\njak aloes \u0142agodzisz \nKa\u017cdy m\u00f3j trud \nz nadzieja Czekam na nowe \nAloes \n________________________________________\nAby nas wesprze\u0107 kliknij tu \n\u2192 https://patronite.pl/langustanapalmie\n\u2192 http://bit.ly/Subskrybuj_Languste\n\n\u2661 Historie pot\u0142uczone\nAnchor \u2192 https://anchor.fm/langusta-na-palmie\nSpreaker \u2192 https://www.spreaker.com/show/historie-potluczone\nSpotify \u2192 https://spoti.fi/2NVIRHb\nApple \u2192 https://apple.co/2ZIPQZv\nGoogle Podcasts \u2192 https://bit.ly/2OlBWH\n\n\u2661  Pismo \u015awi\u0119te: \nAnchor \u2192 https://anchor.fm/langusta-na-palmie\nSpreaker \u2192 https://www.spreaker.com/show/przeczytaj-pismo-swiete-z-langusta\nSpotify \u2192  https://spoti.fi/34nZwLr\nApple \u2192  https://apple.co/33zdwCV\nGoogle Podcasts \u2192 https://bit.ly/3nmaZUc\n\nStrona z kalendarzem o. Adama: \n\u2192 http://www.langustanapalmie.pl\nMo\u017cna nas r\u00f3wnie\u017c znale\u017a\u0107 na Facebooku: \n\u2192 https://www.facebook.com/LangustaNaPalmie\nTwitterze: \n\u2192 https://twitter.com/LangustaPalmowa\nInstagramie: \n\u2192 https://www.instagram.com/langustanapalmie/\n\nZapraszamy.", "link": "https://www.youtube.com/watch?v=Wbv36qQ5xkU", "date_published": "2021-12-19 00:00:00+00:00", "persistent": false, "user": null, "language": "pl-PL"}, {"source": "https://www.youtube.com/feeds/videos.xml?channel_id=UCme4ZOv65uzGADXuvtHkSvA", "title": "Ksi\u0119ga Rut || Rozdzia\u0142 04", "description": "Przeczytajmy razem ca\u0142e Pismo \u015awi\u0119te! Od 1 pa\u017adziernika 2020 czytamy Pismo \u015awi\u0119te, codziennie 1 rozdzia\u0142 \u017cyciodajnego S\u0141OWA BOGA.\nWykorzystano Najnowszy przek\u0142ad Pisma \u015awi\u0119tego z komentarzem opracowany przez Zesp\u00f3\u0142 Biblist\u00f3w Polskich z inicjatywy Towarzystwa \u015awi\u0119tego Paw\u0142a (Edycja \u015awi\u0119tego Paw\u0142a). Pierwszy przek\u0142ad w trzecim tysi\u0105cleciu.\n________________________________________\nAby nas wesprze\u0107 kliknij tu \n\u2192 https://patronite.pl/langustanapalmie\n\u2192 http://bit.ly/Subskrybuj_Languste\n\n\u2661 Historie pot\u0142uczone\nAnchor \u2192 https://anchor.fm/langusta-na-palmie\nSpreaker \u2192 https://www.spreaker.com/show/historie-potluczone\nSpotify \u2192 https://spoti.fi/2NVIRHb\nApple \u2192 https://apple.co/2ZIPQZv\nGoogle Podcasts \u2192 https://bit.ly/2OlBWH\n\n\u2661  Pismo \u015awi\u0119te: \nAnchor \u2192 https://anchor.fm/langusta-na-palmie\nSpreaker \u2192 https://www.spreaker.com/show/przeczytaj-pismo-swiete-z-langusta\nSpotify \u2192  https://spoti.fi/34nZwLr\nApple \u2192  https://apple.co/33zdwCV\nGoogle Podcasts \u2192 https://bit.ly/3nmaZUc\n\nStrona z kalendarzem o. Adama: \n\u2192 http://www.langustanapalmie.pl\nMo\u017cna nas r\u00f3wnie\u017c znale\u017a\u0107 na Facebooku: \n\u2192 https://www.facebook.com/LangustaNaPalmie\nTwitterze: \n\u2192 https://twitter.com/LangustaPalmowa\nInstagramie: \n\u2192 https://www.instagram.com/langustanapalmie/\n\nZapraszamy.", "link": "https://www.youtube.com/watch?v=JHcE2gN0VHY", "date_published": "2021-12-19 00:00:00+00:00", "persistent": false, "user": null, "language": "pl-PL"}, {"source": "https://www.youtube.com/feeds/videos.xml?channel_id=UCme4ZOv65uzGADXuvtHkSvA", "title": "Mocnostronniczy [#49] Metafizyczna codzienno\u015b\u0107", "description": "Takich dw\u00f3ch, jak Ci to nie ma.\nZapraszamy w niedziel\u0119 o godz: 10:oo.\n\n\nzdj\u0119cia, d\u017awi\u0119k, monta\u017c: Marcin Jo\u0144czyk\ngrafika, produkcja serii: Sylwia Smoczy\u0144ska\n\n\n @Langustanapalmie @STREFAWODZA \n________________________________________\nAby nas wesprze\u0107 kliknij tu \n\u2192 https://patronite.pl/langustanapalmie\n\u2192 http://bit.ly/Subskrybuj_Languste\n\n\u2661 Historie pot\u0142uczone\nAnchor \u2192 https://anchor.fm/langusta-na-palmie\nSpreaker \u2192 https://www.spreaker.com/show/historie-potluczone\nSpotify \u2192 https://spoti.fi/2NVIRHb\nApple \u2192 https://apple.co/2ZIPQZv\nGoogle Podcasts \u2192 https://bit.ly/2OlBWH\n\n\u2661  Pismo \u015awi\u0119te: \nAnchor \u2192 https://anchor.fm/langusta-na-palmie\nSpreaker \u2192 https://www.spreaker.com/show/przeczytaj-pismo-swiete-z-langusta\nSpotify \u2192  https://spoti.fi/34nZwLr\nApple \u2192  https://apple.co/33zdwCV\nGoogle Podcasts \u2192 https://bit.ly/3nmaZUc\n\nStrona z kalendarzem o. Adama: \n\u2192 http://www.langustanapalmie.pl\nMo\u017cna nas r\u00f3wnie\u017c znale\u017a\u0107 na Facebooku: \n\u2192 https://www.facebook.com/LangustaNaPalmie\nTwitterze: \n\u2192 https://twitter.com/LangustaPalmowa\nInstagramie: \n\u2192 https://www.instagram.com/langustanapalmie/\n\nZapraszamy.", "link": "https://www.youtube.com/watch?v=od95U8s1i7A", "date_published": "2021-12-19 00:00:00+00:00", "persistent": false, "user": null, "language": "pl-PL"}]