[{"source": "https://www.youtube.com/feeds/videos.xml?channel_id=UC-2JUs_G21BrJ0efehwGkUw", "title": "Scary Pockets \u2018LIFE\u2019 Ad Compilation", "description": "Join our Vinyl Club tier on Patreon to get vinyl every 3 months!\nhttp://modal.scarypocketsfunk.com/patreon\n\nTip Jar: http://modal.scarypocketsfunk.com/tips\n\nListen on Spotify: http://modal.scarypocketsfunk.com/spotify\nSubscribe: http://modal.scarypocketsfunk.com/subscribe\nFacebook: http://modal.scarypocketsfunk.com/facebook\nInstagram: http://modal.scarypocketsfunk.com/instagram\nDiscord: http://modal.scarypocketsfunk.com/discord\n\n#ScaryPockets #Funk #ScaryAds", "link": "https://www.youtube.com/watch?v=rogNNKvlst0", "date_published": "2021-05-28 00:00:00+00:00", "persistent": false, "user": null, "language": "en-US"}]