[{"source": "https://www.bbc.co.uk", "title": "MPs urge changes to 'outdated' gender recognition laws - BBC News", "description": "A committee says legally changing gender remains too difficult and risks entrenching stereotypes.", "link": "https://www.bbc.co.uk/news/uk-politics-59735218", "date_published": "2021-12-22 08:35:29.336205+00:00", "persistent": true, "user": "Thomas Pain", "language": "en-GB", "tags": ["gender", "the left wing", "big brother", "transgender"]}, {"source": "https://www.bbc.co.uk", "title": "McDonald's faces a French fries shortage in Japan - BBC News", "description": "The firm's potato deliveries from North America are being delayed by supply chain disruptions.", "link": "https://www.bbc.co.uk/news/business-59750613", "date_published": "2021-12-22 08:33:03.172804+00:00", "persistent": true, "user": "Thomas Pain", "language": "en-GB"}]