[{"source": "https://www.youtube.com/feeds/videos.xml?channel_id=UC3I2GFN_F8WudD_2jUZbojA", "title": "Liv.e - Full Performance (Live on KEXP at Home)", "description": "http://KEXP.ORG\u200b presents Liv.e performing live, recorded exclusively for KEXP.\n\nSongs:\nLessons from My Mistakes\u2026 But I Lost Your Number\nHow It Made Me Feel\nTo Unplug\nBout My Big Man Batter\nParty Life (Little Beaver cover)\noutro: Untitled / Fantastic - Slum Village \n\nMusicians: \nVocals - Liv.e \nBackground vocals - Aaron Liao, V.C.R, TaRon Lockett \nKeys - Nicholas Semrad \nDrums - TaRon Lockett \nGuitar - Aaron Liao \nBass - Christon Mason \n\nPerformance Video:\nDP - Jackie Radinsky\nEditor - Noah Weisfogel\nProducer - Maya Balkaran\nPA - Isabel Levin\nStylist - Ruth Thao\nSound Engineer - Meji Wahn, Liv.e, Skyler Young\n\nhttps://awal.ffm.to/rn4o4xo\nhttp://kexp.org", "link": "https://www.youtube.com/watch?v=bF9xAKcRajM", "date_published": "2021-02-27 00:00:00+00:00", "persistent": false, "user": null, "language": "en-US"}, {"source": "https://www.youtube.com/feeds/videos.xml?channel_id=UC3I2GFN_F8WudD_2jUZbojA", "title": "Liv.e - Performance & Interview (Live on KEXP at Home)", "description": "http://KEXP.ORG\u200b presents Liv.e sharing a live performance recorded exclusively for KEXP and talking with Larry Mizell, Jr., host of The Afternoon Show. Recorded February 22, 2021.\n\nSongs:\nLessons from My Mistakes\u2026 But I Lost Your Number\nHow It Made Me Feel\nTo Unplug\nBout My Big Man Batter\nParty Life (Little Beaver cover)\noutro: Untitled / Fantastic - Slum Village \n\nMusicians: \nVocals - Liv.e \nBackground vocals - Aaron Liao, V.C.R, TaRon Lockett \nKeys - Nicholas Semrad \nDrums - TaRon Lockett \nGuitar - Aaron Liao \nBass - Christon Mason \n\nPerformance Video:\nDP - Jackie Radinsky\nEditor - Noah Weisfogel\nProducer - Maya Balkaran\nPA - Isabel Levin\nStylist - Ruth Thao\nSound Engineer - Meji Wahn, Liv.e, Skyler Young\n\nhttps://awal.ffm.to/rn4o4xo\nhttp://kexp.org", "link": "https://www.youtube.com/watch?v=9CNUNee-VCI", "date_published": "2021-02-26 00:00:00+00:00", "persistent": false, "user": null, "language": "en-US"}]