[{"source": "http://rss.cnn.com/rss/edition.rss", "title": "Trump allies are angling for election jobs. That may have consequences", "description": "As former President Donald Trump prepares for a potential comeback bid in 2024, his allies are flocking to election jobs all the way down to the local level in key battleground states, raising new concerns that the election officials who blocked Trump's efforts to overturn the 2020 election won't be there the next time around.", "link": "https://www.cnn.com/2021/12/06/politics/trump-allies-local-elections/index.html", "date_published": "2021-12-06 22:06:00+00:00", "persistent": false, "user": null, "language": "en-US"}]