[{"source": "https://www.youtube.com/feeds/videos.xml?channel_id=UCQSpnDG3YsFNf5-qHocF-WQ", "title": "What Does Formatting Actually Do, Anyway?", "description": "And what is the different with Quick Format?\n\u21d2 Become a channel member for exclusive features! Check it out here: https://www.youtube.com/ThioJoe/join\n\n\u25bc Time Stamps: \u25bc\n0:00 - Intro & Basics\n0:38 - Formatting in Windows\n2:03 - Quick Format\n3:00 - Non-Quick Format\n4:07 - Demonstration\n4:52 - HDD Architecture\n8:33 - Low Level Formatting\n11:03 - SSD Architecture\n14:09 - File Storage on SSD\n15:23 - Conclusion\n\n\u25ac\u25ac\u25ac\u25ac\u25ac\u25ac\u25ac\u25ac\u25ac\u25ac\u25ac\u25ac\u25ac\u25ac\u25ac\u25ac\u25ac\u25ac\u25ac\u25ac\u25ac\u25ac\u25ac\u25ac\u25ac\u25ac\nMerch \u21e8 https://teespring.com/stores/thiojoe\n\u21e8 http://Instagram.com/ThioJoe\n\u21e8 http://Twitter.com/ThioJoe\n\u21e8 http://Facebook.com/ThioJoeTV\nMy Gear & Equipment \u21e8 https://kit.co/ThioJoe\n\u25ac\u25ac\u25ac\u25ac\u25ac\u25ac\u25ac\u25ac\u25ac\u25ac\u25ac\u25ac\u25ac\u25ac\u25ac\u25ac\u25ac\u25ac\u25ac\u25ac\u25ac\u25ac\u25ac\u25ac\u25ac\u25ac\n\n#Computers #Windows #Tech #ThioJoe", "link": "https://www.youtube.com/watch?v=NiefQwuNtjg", "date_published": "2021-04-04 00:00:00+00:00", "persistent": false, "user": null, "language": "en-US"}]