[{"source": "https://www.scmp.com", "title": "\u2018Picking quarrels and provoking trouble\u2019: how China\u2019s catch-all crime muzzles dissent | South China Morning Post", "description": "\u2018Picking quarrels and provoking trouble\u2019: how China\u2019s catch-all crime muzzles dissent | South China Morning Post", "link": "https://www.scmp.com/news/china/politics/article/3146188/picking-quarrels-and-provoking-trouble-how-chinas-catch-all", "date_published": "2021-08-25 16:02:03+00:00", "persistent": true, "user": "rumpel", "language": "en", "tags": ["propaganda", "censorship", "surveillance", "china", "misinformation"]}]