[{"source": "https://www.youtube.com/feeds/videos.xml?channel_id=UCSJPFQdZwrOutnmSFYtbstA", "title": "Spider-Man: No Way Home - Nostalgia Bait Or The Real Deal?", "description": "The trailer for Spider-Man: No Way Home seems to have everyone excited. Join me as I take a closer look and offer my thoughts on what this film could represent for the MCU.", "link": "https://www.youtube.com/watch?v=LyrKBaEuQ1w", "date_published": "2021-08-26 00:00:00+00:00", "persistent": false, "user": null, "language": "en-US"}]