[{"source": "https://www.youtube.com/feeds/videos.xml?channel_id=UCqg5FCR7NrpvlBWMXdt-5Vg", "title": "3 Minute Reviews' Favorite Games of 2021", "description": "KC, Jesse, Amy, Will and Elise are here to provide you with their favorite games they reviewed on 3 Minute Reviews in 2021.\n\nJoin YouTube Memberships and support our content for Early Access to new videos, exclusive Discord perks & more for just $2 per month \u25ba\u25ba https://www.youtube.com/channel/UCqg5FCR7NrpvlBWMXdt-5Vg/join\n\nSubscribe to Escapist Magazine! \u25ba\u25ba http://bit.ly/Sub2Escapist\n\nWant to see the next episode a week early? Check out http://www.escapistmagazine.com for the latest episodes of your favorite shows.\n\n---\n\n\n\n---\n\n\nZero Punctuation Merch Store \u25ba\u25bahttps://teespring.com/stores/the-escapist-store\nJoin us on Twitch \u25ba\u25ba https://www.twitch.tv/the_escapist_official\nLike us on Facebook \u25ba\u25ba http://www.facebook.com/EscapistMag\nFollow us on Twitter \u25ba\u25ba https://twitter.com/EscapistMag", "link": "https://www.youtube.com/watch?v=uPEhR-7ATFI", "date_published": "2021-12-31 00:00:00+00:00", "persistent": false, "user": null, "language": "en-US"}, {"source": "https://www.youtube.com/feeds/videos.xml?channel_id=UCqg5FCR7NrpvlBWMXdt-5Vg", "title": "F.I.S.T. - Forged in Shadow Torch is A Surprisingly Good Metroidvania", "description": "Sponsored by F.I.S.T. - Forged in Shadow Torch.\n\nMarty takes a look at F.I.S.T. - Forged in Shadow Torch in this sponsored video, which actually happens to be a very a good metroidvania. \n\nJoin YouTube Memberships and support our content for Early Access to new videos, exclusive Discord perks & more for just $2 per month \u25ba\u25ba https://www.youtube.com/channel/UCqg5FCR7NrpvlBWMXdt-5Vg/join\n\nSubscribe to Escapist Magazine! \u25ba\u25ba http://bit.ly/Sub2Escapist\n\nWant to see the next episode a week early? Check out http://www.escapistmagazine.com for the latest episodes of your favorite shows.\n\n---\n\n\n\n---\n\n\nZero Punctuation Merch Store \u25ba\u25bahttps://teespring.com/stores/the-escapist-store\nJoin us on Twitch \u25ba\u25ba https://www.twitch.tv/the_escapist_official\nLike us on Facebook \u25ba\u25ba http://www.facebook.com/EscapistMag\nFollow us on Twitter \u25ba\u25ba https://twitter.com/EscapistMag\n\n#Sponsored", "link": "https://www.youtube.com/watch?v=lJxgvJ7g-vA", "date_published": "2021-12-31 00:00:00+00:00", "persistent": false, "user": null, "language": "en-US"}]